{
  "Future Health Solutions": {
    "id": "future_health_solutions",
    "description": "Health, food, and life support systems",
    "levels": [
      {
        "level": 1,
        "xp": 0,
        "components": [],
        "rewards": [
          {
            "name": "Habitat"
          },
          {
            "name": "Basic Habitat Modules"
          },
          {
            "name": "Advanced Habitat Modules"
          }
        ]
      },
      {
        "level": 2,
        "xp": 200,
        "components": [
          {
            "id": "bar_wolfram",
            "points": 1
          }
        ],
        "rewards": [
          {
            "name": "Regeneration Chamber"
          }
        ]
      },
      {
        "level": 3,
        "xp": 1500,
        "components": [
          {
            "id": "bar_wolfram",
            "points": 1
          },
          {
            "id": "wolfram_wire",
            "points": 5
          }
        ],
        "rewards": [
          {
            "name": "Medtool"
          }
        ]
      },
      {
        "level": 4,
        "xp": 6400,
        "components": [
          {
            "id": "titanium_rod",
            "points": 4
          },
          {
            "id": "titanium_sheet",
            "points": 15
          }
        ],
        "rewards": [
          {
            "name": "LEM Station"
          }
        ]
      },
      {
        "level": 5,
        "xp": 17600,
        "components": [
          {
            "id": "powder_calcium",
            "points": 12
          },
          {
            "id": "powder_wolfram",
            "points": 18
          }
        ],
        "rewards": [
          {
            "name": "Lesser Dietician LEM"
          },
          {
            "name": "Lesser Irrigator LEM"
          }
        ]
      },
      {
        "level": 6,
        "xp": 37800,
        "components": [
          {
            "id": "ceramics",
            "points": 25
          }
        ],
        "rewards": [
          {
            "name": "Food Station"
          }
        ]
      },
      {
        "level": 7,
        "xp": 69700,
        "components": [
          {
            "id": "glass",
            "points": 46
          }
        ],
        "rewards": [
          {
            "name": "Inventory Upgrade (+8)"
          }
        ]
      },
      {
        "level": 8,
        "xp": 116000,
        "components": [
          {
            "id": "chemicals",
            "points": 46
          }
        ],
        "rewards": [
          {
            "name": "Dietician LEM"
          },
          {
            "name": "Irrigator LEM"
          }
        ]
      },
      {
        "level": 9,
        "xp": 179400,
        "components": [
          {
            "id": "hardening_agent",
            "points": 60
          },
          {
            "id": "pressurized_helium",
            "points": 20
          }
        ],
        "rewards": [
          {
            "name": "Compounder"
          }
        ]
      },
      {
        "level": 10,
        "xp": 262600,
        "components": [
          {
            "id": "liquid_helium",
            "points": 120
          }
        ],
        "rewards": [
          {
            "name": "Resister LEM"
          }
        ]
      },
      {
        "level": 11,
        "xp": 368300,
        "components": [
          {
            "id": "ion_injector",
            "points": 246
          }
        ],
        "rewards": [
          {
            "name": "Greater Irrigator LEM"
          },
          {
            "name": "Greater Dietician LEM"
          }
        ]
      }
    ]
  },
  "Selenian Corporation": {
    "id": "selenian_corporation",
    "description": "Factories and production facilities",
    "levels": [
      {
        "level": 1,
        "xp": 0,
        "components": [],
        "rewards": [
          {
            "name": "Base Core"
          },
          {
            "name": "Basic Item Printer"
          },
          {
            "name": "Ore Excavator"
          },
          {
            "name": "Smelter"
          },
          {
            "name": "Habitat"
          }
        ]
      },
      {
        "level": 2,
        "xp": 200,
        "components": [
          {
            "id": "bar_titanium",
            "points": 1
          }
        ],
        "rewards": [
          {
            "name": "Fabricator"
          }
        ]
      },
      {
        "level": 3,
        "xp": 1500,
        "components": [
          {
            "id": "bar_titanium",
            "points": 1
          },
          {
            "id": "titanium_rod",
            "points": 5
          }
        ],
        "rewards": [
          {
            "name": "Inventory Upgrade (+8)"
          }
        ]
      },
      {
        "level": 4,
        "xp": 6400,
        "components": [
          {
            "id": "titanium_rod",
            "points": 4
          },
          {
            "id": "titanium_sheet",
            "points": 16
          }
        ],
        "rewards": [
          {
            "name": "Furnace"
          }
        ]
      },
      {
        "level": 5,
        "xp": 17600,
        "components": [
          {
            "id": "titanium_beam",
            "points": 35
          },
          {
            "id": "titanium_sheet",
            "points": 12
          }
        ],
        "rewards": [
          {
            "name": "Greater Miner LEM"
          }
        ]
      },
      {
        "level": 6,
        "xp": 37800,
        "components": [
          {
            "id": "tube",
            "points": 25
          }
        ],
        "rewards": [
          {
            "name": "Helium-3 Extractor"
          }
        ]
      },
      {
        "level": 7,
        "xp": 69700,
        "components": [
          {
            "id": "glass",
            "points": 70
          },
          {
            "id": "synthetic_silicon",
            "points": 46
          }
        ],
        "rewards": [
          {
            "name": "Large Habitat"
          }
        ]
      },
      {
        "level": 8,
        "xp": 116000,
        "components": [
          {
            "id": "electronics",
            "points": 116
          },
          {
            "id": "synthetic_silicon",
            "points": 46
          }
        ],
        "rewards": [
          {
            "name": "Mega Press"
          }
        ]
      },
      {
        "level": 9,
        "xp": 179400,
        "components": [
          {
            "id": "impeller",
            "points": 120
          }
        ],
        "rewards": [
          {
            "name": "Refinery"
          },
          {
            "name": "Sulfur Extractor"
          }
        ]
      },
      {
        "level": 10,
        "xp": 262600,
        "components": [
          {
            "id": "turbine",
            "points": 175
          }
        ],
        "rewards": [
          {
            "name": "Assembler"
          }
        ]
      },
      {
        "level": 11,
        "xp": 368300,
        "components": [
          {
            "id": "scanner",
            "points": 246
          }
        ],
        "rewards": [
          {
            "name": "Greater Endurancegiver LEM"
          },
          {
            "name": "Greater Lifegiver LEM"
          }
        ]
      }
    ]
  },
  "Griffith Blue Corporation": {
    "id": "griffith_blue_corporation",
    "description": "Military defense and weapons",
    "levels": [
      {
        "level": 1,
        "xp": 0,
        "components": [],
        "rewards": [
          {
            "name": "Basic Platforms"
          },
          {
            "name": "Advanced Platforms"
          },
          {
            "name": "Platform Modules"
          }
        ]
      },
      {
        "level": 2,
        "xp": 200,
        "components": [
          {
            "id": "bar_titanium",
            "points": 1
          }
        ],
        "rewards": [
          {
            "name": "UPP-7 Pistol"
          }
        ]
      },
      {
        "level": 3,
        "xp": 1500,
        "components": [
          {
            "id": "titanium_rod",
            "points": 5
          },
          {
            "id": "wolfram_wire",
            "points": 5
          }
        ],
        "rewards": [
          {
            "name": "Grenade"
          }
        ]
      },
      {
        "level": 4,
        "xp": 6400,
        "components": [
          {
            "id": "titanium_sheet",
            "points": 15
          },
          {
            "id": "wolfram_plate",
            "points": 15
          }
        ],
        "rewards": [
          {
            "name": "Equipment Upgrade Station"
          }
        ]
      },
      {
        "level": 5,
        "xp": 17600,
        "components": [
          {
            "id": "titanium_housing",
            "points": 35
          },
          {
            "id": "titanium_sheet",
            "points": 12
          }
        ],
        "rewards": [
          {
            "name": "War Bonds (60)"
          }
        ]
      },
      {
        "level": 6,
        "xp": 37800,
        "components": [
          {
            "id": "stabilizer",
            "points": 35
          }
        ],
        "rewards": [
          {
            "name": "Defense Turret"
          }
        ]
      },
      {
        "level": 7,
        "xp": 69700,
        "components": [
          {
            "id": "inductor",
            "points": 70
          },
          {
            "id": "stabilizer",
            "points": 35
          }
        ],
        "rewards": [
          {
            "name": "War Bonds (80)"
          }
        ]
      },
      {
        "level": 8,
        "xp": 116000,
        "components": [
          {
            "id": "applicator",
            "points": 46
          }
        ],
        "rewards": [
          {
            "name": "Inventory Upgrade (+8)"
          }
        ]
      },
      {
        "level": 9,
        "xp": 179400,
        "components": [
          {
            "id": "battery",
            "points": 120
          },
          {
            "id": "nozzle",
            "points": 45
          }
        ],
        "rewards": [
          {
            "name": "Defense Tower"
          }
        ]
      },
      {
        "level": 10,
        "xp": 262600,
        "components": [
          {
            "id": "lens",
            "points": 175
          }
        ],
        "rewards": [
          {
            "name": "War Bonds (100)"
          }
        ]
      },
      {
        "level": 11,
        "xp": 368299,
        "components": [
          {
            "id": "condenser",
            "points": 246
          }
        ],
        "rewards": [
          {
            "name": "Greater Shieldgiver LEM"
          },
          {
            "name": "Greater Lifegiver LEM"
          }
        ]
      }
    ]
  },
  "Moon Energy Corporation": {
    "id": "moon_energy_corporation",
    "description": "Energy generation and research",
    "levels": [
      {
        "level": 1,
        "xp": 0,
        "components": [],
        "rewards": [
          {
            "name": "Solar Generator v.1"
          },
          {
            "name": "Analyzing Station"
          }
        ]
      },
      {
        "level": 2,
        "xp": 200,
        "components": [
          {
            "id": "bar_wolfram",
            "points": 1
          }
        ],
        "rewards": [
          {
            "name": "Recipe Station"
          }
        ]
      },
      {
        "level": 3,
        "xp": 1500,
        "components": [
          {
            "id": "ore_calcium",
            "points": 5
          }
        ],
        "rewards": [
          {
            "name": "Map"
          }
        ]
      },
      {
        "level": 4,
        "xp": 6400,
        "components": [
          {
            "id": "calcite_sheets",
            "points": 15
          },
          {
            "id": "block_calcium",
            "points": 4
          }
        ],
        "rewards": [
          {
            "name": "Lesser Infiltrator LEM"
          }
        ]
      },
      {
        "level": 5,
        "xp": 17600,
        "components": [
          {
            "id": "rotor",
            "points": 45
          }
        ],
        "rewards": [
          {
            "name": "Wind Turbine v.1"
          }
        ]
      },
      {
        "level": 6,
        "xp": 37800,
        "components": [
          {
            "id": "heat_sheet",
            "points": 25
          }
        ],
        "rewards": [
          {
            "name": "Base Core Amplifier v.2"
          }
        ]
      },
      {
        "level": 7,
        "xp": 69700,
        "components": [
          {
            "id": "chemicals",
            "points": 70
          },
          {
            "id": "helium",
            "points": 5
          }
        ],
        "rewards": [
          {
            "name": "Greater Infiltrator LEM"
          }
        ]
      },
      {
        "level": 8,
        "xp": 116000,
        "components": [
          {
            "id": "valve",
            "points": 100
          }
        ],
        "rewards": [
          {
            "name": "Solar Generator v.2"
          }
        ]
      },
      {
        "level": 9,
        "xp": 179400,
        "components": [
          {
            "id": "electromagnetic_coil",
            "points": 120
          }
        ],
        "rewards": [
          {
            "name": "Base Core Amplifier v.2"
          }
        ]
      },
      {
        "level": 10,
        "xp": 262600,
        "components": [
          {
            "id": "generator",
            "points": 175
          }
        ],
        "rewards": [
          {
            "name": "Wind Turbine v.2"
          }
        ]
      },
      {
        "level": 11,
        "xp": 368300,
        "components": [
          {
            "id": "laser_emitter",
            "points": 246
          }
        ],
        "rewards": [
          {
            "name": "Inventory Upgrade (+8)"
          }
        ]
      }
    ]
  },
  "Clever Robotics": {
    "id": "clever_robotics",
    "description": "Logistics, transportation, and automation",
    "levels": [
      {
        "level": 1,
        "xp": 0,
        "components": [],
        "rewards": [
          {
            "name": "Corporate Terminal"
          },
          {
            "name": "Orbital Cargo Launcher"
          },
          {
            "name": "Rail v.1"
          },
          {
            "name": "Rail Support"
          },
          {
            "name": "Rail Connector"
          }
        ]
      },
      {
        "level": 2,
        "xp": 200,
        "components": [
          {
            "id": "bar_wolfram",
            "points": 1
          }
        ],
        "rewards": [
          {
            "name": "Personal Storage"
          }
        ]
      },
      {
        "level": 3,
        "xp": 1500,
        "components": [
          {
            "id": "bar_wolfram",
            "points": 1
          },
          {
            "id": "wolfram_wire",
            "points": 5
          }
        ],
        "rewards": [
          {
            "name": "Storage Depot v.1"
          }
        ]
      },
      {
        "level": 4,
        "xp": 6400,
        "components": [
          {
            "id": "wolfram_plate",
            "points": 15
          },
          {
            "id": "wolfram_wire",
            "points": 4
          }
        ],
        "rewards": [
          {
            "name": "Building Drone"
          }
        ]
      },
      {
        "level": 5,
        "xp": 17600,
        "components": [
          {
            "id": "titanium_housing",
            "points": 35
          },
          {
            "id": "wolfram_plate",
            "points": 12
          }
        ],
        "rewards": [
          {
            "name": "Multirail 3"
          },
          {
            "name": "Rail Modulator 3"
          }
        ]
      },
      {
        "level": 6,
        "xp": 37800,
        "components": [
          {
            "id": "heat_sheet",
            "points": 25
          },
          {
            "id": "titanium_housing",
            "points": 25
          }
        ],
        "rewards": [
          {
            "name": "Rail v.2"
          }
        ]
      },
      {
        "level": 7,
        "xp": 69700,
        "components": [
          {
            "id": "stator",
            "points": 46
          }
        ],
        "rewards": [
          {
            "name": "Cargo Dispatcher"
          },
          {
            "name": "Cargo Receiver"
          }
        ]
      },
      {
        "level": 8,
        "xp": 116000,
        "components": [
          {
            "id": "nozzle",
            "points": 46
          },
          {
            "id": "supermagnet",
            "points": 116
          }
        ],
        "rewards": [
          {
            "name": "Storage Depot v.2"
          }
        ]
      },
      {
        "level": 9,
        "xp": 179400,
        "components": [
          {
            "id": "electronics",
            "points": 46
          },
          {
            "id": "hardening_agent",
            "points": 70
          }
        ],
        "rewards": [
          {
            "name": "Large Personal Storage"
          }
        ]
      },
      {
        "level": 10,
        "xp": 262600,
        "components": [
          {
            "id": "pressurized_helium",
            "points": 10
          },
          {
            "id": "pump",
            "points": 175
          }
        ],
        "rewards": [
          {
            "name": "Multirail 5"
          },
          {
            "name": "Rail Modulator 5"
          }
        ]
      },
      {
        "level": 11,
        "xp": 368300,
        "components": [
          {
            "id": "electromagnet",
            "points": 246
          }
        ],
        "rewards": [
          {
            "name": "Rail v.3"
          }
        ]
      },
      {
        "level": 12,
        "xp": 499200,
        "components": [
          {
            "id": "pressure_tank",
            "points": 210
          }
        ],
        "rewards": [
          {
            "name": "Multistorage"
          }
        ]
      },
      {
        "level": 13,
        "xp": 658000,
        "components": [
          {
            "id": "superconductor",
            "points": 400
          }
        ],
        "rewards": [
          {
            "name": "Expandable Storage"
          }
        ]
      }
    ]
  }
}
